webgui_jupyter_widgets/__init__.py
webgui_jupyter_widgets/_version.py
webgui_jupyter_widgets/html.py
webgui_jupyter_widgets/widget.py
webgui_jupyter_widgets/js/__init__.py
webgui_jupyter_widgets/js/__main__.py
webgui_jupyter_widgets/js/webgui.js
webgui_jupyter_widgets/js/webgui_jupyter_widgets.js
webgui_jupyter_widgets/labextension/package.json
webgui_jupyter_widgets/labextension/static/367.b31d0ca593df9b646825.js
webgui_jupyter_widgets/labextension/static/480.be81e4ede8ceaa1dc831.js
webgui_jupyter_widgets/labextension/static/568.881903b5baab273a1606.js
webgui_jupyter_widgets/labextension/static/remoteEntry.fb31647e2334dd90b029.js
webgui_jupyter_widgets/labextension/static/style.js
webgui_jupyter_widgets/labextension/static/third-party-licenses.json
webgui_jupyter_widgets/nbextension/extension.js
webgui_jupyter_widgets/nbextension/index.js
webgui_jupyter_widgets/nbextension/index.js.map
webgui_jupyter_widgets/nbextension/webgui.js
webgui_jupyter_widgets/tests/__init__.py
webgui_jupyter_widgets/tests/conftest.py
webgui_jupyter_widgets/tests/test_example.py
webgui_jupyter_widgets/tests/test_nbextension_path.py
webgui_jupyter_widgets-0.2.36.data/data/etc/jupyter/nbconfig/notebook.d/webgui_jupyter_widgets.json
webgui_jupyter_widgets-0.2.36.data/data/share/jupyter/labextensions/webgui_jupyter_widgets/install.json
webgui_jupyter_widgets-0.2.36.data/data/share/jupyter/labextensions/webgui_jupyter_widgets/package.json
webgui_jupyter_widgets-0.2.36.data/data/share/jupyter/labextensions/webgui_jupyter_widgets/static/367.b31d0ca593df9b646825.js
webgui_jupyter_widgets-0.2.36.data/data/share/jupyter/labextensions/webgui_jupyter_widgets/static/480.be81e4ede8ceaa1dc831.js
webgui_jupyter_widgets-0.2.36.data/data/share/jupyter/labextensions/webgui_jupyter_widgets/static/568.881903b5baab273a1606.js
webgui_jupyter_widgets-0.2.36.data/data/share/jupyter/labextensions/webgui_jupyter_widgets/static/remoteEntry.fb31647e2334dd90b029.js
webgui_jupyter_widgets-0.2.36.dist-info/LICENSE.txt
webgui_jupyter_widgets-0.2.36.dist-info/METADATA
webgui_jupyter_widgets-0.2.36.dist-info/WHEEL
webgui_jupyter_widgets-0.2.36.dist-info/top_level.txt
webgui_jupyter_widgets-0.2.36.dist-info/RECORD
